
[
    {
      "id": 1,
      "title": "Spaghetti Carbonara",
      "summary": "A classic Italian pasta dish with eggs, cheese, bacon, and black pepper.",
      "image": "https://via.placeholder.com/150",
      "ingredients": [
        "200g spaghetti",
        "100g pancetta",
        "2 large eggs",
        "50g Parmesan cheese",
        "Freshly ground black pepper"
      ],
      "instructions": "Cook the spaghetti according to the package instructions. In a pan, fry pancetta until crispy. Beat eggs and mix with Parmesan. Toss the hot spaghetti with pancetta and egg mixture. Serve with freshly ground black pepper."
    },
    {
      "id": 2,
      "title": "Chicken Tikka Masala",
      "summary": "Chunks of grilled chicken (tikka) cooked in a smooth buttery & creamy tomato-based gravy.",
      "image": "https://via.placeholder.com/150",
      "ingredients": [
        "500g chicken breast",
        "200g yogurt",
        "1 tbsp garam masala",
        "1 onion",
        "200g tomatoes",
        "100ml cream"
      ],
      "instructions": "Marinate the chicken in yogurt and spices for 1 hour. Grill or cook the chicken. In a pan, sauté onions, add tomatoes and spices. Add the grilled chicken and simmer. Stir in cream before serving."
    }
  ]
  